infiltra
