Metadata-Version: 2.1
Name: infiltra
Version: 2.4
Summary: CLI Based to that Automates Various Pentest Tools
Home-page: UNKNOWN
Author: @jivy26
Author-email: jivy26@gmail.com
License: MIT
Keywords: infiltra penetration cybersecurity scanning
Platform: UNKNOWN
Requires-Dist: colorama
